xinhe-0.0.0.dist-info/METADATA
xinhe-0.0.0.dist-info/WHEEL
xinhe-0.0.0.dist-info/entry_points.txt
xinhe/__init__.py
xinhe-0.0.0.dist-info/RECORD
